<bug id='27709' author='surgan12' open_date='2019-04-10T09:47:58Z' closed_time='2019-08-09T16:56:49Z'>
	<summary>Link to the definiton tf.image broken</summary>
	<description>
&lt;denchmark-h:h3&gt;On the page&lt;/denchmark-h&gt;

&lt;denchmark-link:https://www.tensorflow.org/api_docs/python/tf/image&gt;https://www.tensorflow.org/api_docs/python/tf/image&lt;/denchmark-link&gt;

&lt;denchmark-h:h3&gt;The link Under heading&lt;/denchmark-h&gt;

Module tf.Image
&lt;denchmark-link:https://www.tensorflow.org/code/stable/tensorflow/_api/v1/image/__init__.py&gt;https://www.tensorflow.org/code/stable/tensorflow/_api/v1/image/__init__.py&lt;/denchmark-link&gt;


	</description>
	<comments>
		<comment id='1' author='surgan12' date='2019-08-09T16:56:49Z'>
		This one looks fixed: &lt;denchmark-link:https://www.tensorflow.org/api_docs/python/tf/image&gt;https://www.tensorflow.org/api_docs/python/tf/image&lt;/denchmark-link&gt;

		</comment>
	</comments>
</bug>