<bug id='1043' author='arraydude' open_date='2020-02-03T20:06:39Z' closed_time='2020-05-20T18:09:27Z'>
	<summary>height parameter is not working for pydeck_chart()</summary>
	<description>
&lt;denchmark-h:h1&gt;Summary&lt;/denchmark-h&gt;

There is no way to set the height or width for a pydeck chart, neither with a height parameter or using Deck object
&lt;denchmark-h:h2&gt;Expected behavior:&lt;/denchmark-h&gt;

We should able to set it with pdk.ViewState()
&lt;denchmark-h:h2&gt;Actual behavior:&lt;/denchmark-h&gt;

The component is resetting initialViewState height and width from the props but pydeck_chart() has no height or width parameter
	</description>
	<comments>
		<comment id='1' author='arraydude' date='2020-05-20T18:09:27Z'>
		Looks to be fixed in latest version (0.60.0)
We can set the height via pdk.ViewState() as well as via props to pydeck_chart, but height prop isn't exposed to the user, it's used by FullScreenWrapper and WideMode.
&lt;denchmark-code&gt;st.pydeck_chart(
    pdk.Deck(
        initial_view_state=pdk.ViewState(
            latitude=37.76, longitude=-122.4, zoom=11, pitch=50,
            height=500, width=500
        ),
        layers=[
            pdk.Layer(
&lt;/denchmark-code&gt;

		</comment>
	</comments>
</bug>