{"BR": {"BR_id": "116", "BR_author": "ethanwharris", "BRopenT": "2018-04-23T12:31:20Z", "BRcloseT": "2018-04-23T12:59:27Z", "BR_text": {"BRsummary": "Tqdm nests generator, causes overflow", "BRdescription": "\n Leak with tqdm, gets deeper as time goes on\n \t"}, "comments": {}}, "commit": {"commit_id": "1c3cd51d12d384681c46ce50da1aaca64463fcd8", "commit_author": "Ethan Harris", "commitT": "2018-04-23 13:59:26+01:00", "commit_complexity": {"commit_NLOC": "None", "commit_CCN": "None", "commit_Nprams": "None"}, "changed_files": {"file_0": {"file_change_type": "MODIFY", "file_Nmethod": 1, "file_old_name": "bink\\bink.py", "file_new_name": "bink\\bink.py", "file_complexity": {"file_NLOC": "213", "file_CCN": "38", "file_NToken": "1934"}, "hunks": {"hunk_0": {"Ismethod": 1, "added_lines": "147,148,149", "deleted_lines": "147", "method_info": {"method_name": "_test_loop", "method_params": "self,state,callbacks,pass_state,batch_loader,num_steps", "method_startline": "138", "method_endline": "171", "method_complexity": {"method_NLOC": "23", "method_CCN": "7", "method_NToken": "208", "method_nesting_level": "1"}}}}}, "file_1": {"file_change_type": "MODIFY", "file_Nmethod": 4, "file_old_name": "bink\\callbacks\\printer.py", "file_new_name": "bink\\callbacks\\printer.py", "file_complexity": {"file_NLOC": "35", "file_CCN": "11", "file_NToken": "393"}, "hunks": {"hunk_0": {"Ismethod": 1, "added_lines": "38", "deleted_lines": "38", "method_info": {"method_name": "on_start_validation", "method_params": "self,state", "method_startline": "36", "method_endline": "38", "method_complexity": {"method_NLOC": "3", "method_CCN": "1", "method_NToken": "46", "method_nesting_level": "1"}}}, "hunk_1": {"Ismethod": 1, "added_lines": "26", "deleted_lines": "26", "method_info": {"method_name": "on_start_training", "method_params": "self,state", "method_startline": "24", "method_endline": "26", "method_complexity": {"method_NLOC": "3", "method_CCN": "1", "method_NToken": "42", "method_nesting_level": "1"}}}, "hunk_2": {"Ismethod": 1, "added_lines": "29", "deleted_lines": null, "method_info": {"method_name": "on_step_training", "method_params": "self,state", "method_startline": "28", "method_endline": "30", "method_complexity": {"method_NLOC": "3", "method_CCN": "1", "method_NToken": "26", "method_nesting_level": "1"}}}, "hunk_3": {"Ismethod": 1, "added_lines": "41", "deleted_lines": null, "method_info": {"method_name": "on_step_validation", "method_params": "self,state", "method_startline": "40", "method_endline": "42", "method_complexity": {"method_NLOC": "3", "method_CCN": "1", "method_NToken": "26", "method_nesting_level": "1"}}}}}}}}