{"BR": {"BR_id": "330", "BR_author": "srikris", "BRopenT": "2018-03-02T21:03:35Z", "BRcloseT": "2018-03-13T18:10:05Z", "BR_text": {"BRsummary": "Mention in API docs and user guide that show does it inline in iPython notebook", "BRdescription": "\n \n No description provided.\n \n \t"}, "comments": {}}, "commit": {"commit_id": "6cddd843e15405f32161100871a87a2c44bd9ccd", "commit_author": "Zach Nation", "commitT": "2018-03-13 11:10:04-07:00", "commit_complexity": {"commit_NLOC": "None", "commit_CCN": "None", "commit_Nprams": "None"}, "changed_files": {"file_0": {"file_change_type": "MODIFY", "file_Nmethod": 0, "file_old_name": "userguide\\vis\\README.md", "file_new_name": "userguide\\vis\\README.md", "file_complexity": {"file_NLOC": "None", "file_CCN": "None", "file_NToken": "None"}, "hunks": {"hunk_0": {"Ismethod": 0, "added_lines": "43,44,45,46,47", "deleted_lines": "43,44,45"}}}}}}