<commit id='aa19df1bbbc0b92a4e3d0b529941100a129be192' author='Quan (Andy) Gan' date='2020-08-18 09:29:05+08:00'>
	<dmm_unit complexity='0.9444444444444444' interfacing='0.9444444444444444' size='1.0'></dmm_unit>
	<modification change_type='MODIFY' old_name='python\dgl\batch.py' new_name='python\dgl\batch.py'>
		<file_info nloc='280' complexity='64' token_count='1379'></file_info>
		<method name='batch' parameters='graphs,ndata,edata,node_attrs,edge_attrs'>
				<method_info nloc='195' complexity='26' token_count='566' nesting_level='0' start_line='12' end_line='218'></method_info>
			<added_lines>171,176,177,178,179,180,182,183,184,185,186,187,188</added_lines>
			<deleted_lines>174,175,176,177,178,179,180,182,183,184,185,187</deleted_lines>
		</method>
		<modified_lines>
			<added_lines>3</added_lines>
			<deleted_lines></deleted_lines>
		</modified_lines>
	</modification>
	<modification change_type='DELETE' old_name='test.py' new_name='test.py'>
		<file_info nloc='None' complexity='None' token_count='None'></file_info>
	</modification>
	<modification change_type='MODIFY' old_name='tests\compute\test_batched_heterograph.py' new_name='tests\compute\test_batched_heterograph.py'>
		<file_info nloc='259' complexity='27' token_count='4112'></file_info>
		<method name='test_topology' parameters='gs,idtype'>
				<method_info nloc='44' complexity='5' token_count='546' nesting_level='0' start_line='46' end_line='105'></method_info>
			<added_lines>46,48,49,50</added_lines>
			<deleted_lines>46,47,48,49,50,51,52,53,54,55</deleted_lines>
		</method>
		<method name='test_topology' parameters='idtype'>
				<method_info nloc='51' complexity='5' token_count='689' nesting_level='0' start_line='44' end_line='110'></method_info>
			<added_lines>44,46,48,49,50</added_lines>
			<deleted_lines>44,46,47,48,49,50,51,52,53,54,55</deleted_lines>
		</method>
		<modified_lines>
			<added_lines>4,8</added_lines>
			<deleted_lines>7</deleted_lines>
		</modified_lines>
	</modification>
	<modification change_type='MODIFY' old_name='tests\compute\test_pickle.py' new_name='tests\compute\test_pickle.py'>
		<file_info nloc='145' complexity='25' token_count='1572'></file_info>
		<modified_lines>
			<added_lines>135</added_lines>
			<deleted_lines>135</deleted_lines>
		</modified_lines>
	</modification>
	<modification change_type='MODIFY' old_name='tests\test_utils\graph_cases.py' new_name='tests\test_utils\graph_cases.py'>
		<file_info nloc='117' complexity='26' token_count='1727'></file_info>
		<method name='two_hetero_batch' parameters=''>
				<method_info nloc='12' complexity='1' token_count='170' nesting_level='0' start_line='114' end_line='125'></method_info>
			<added_lines>114,115,116,117,118,119,120,121,122,123,124,125</added_lines>
			<deleted_lines></deleted_lines>
		</method>
		<method name='two_hetero_batch_with_isolated_ntypes' parameters=''>
				<method_info nloc='12' complexity='1' token_count='210' nesting_level='0' start_line='128' end_line='139'></method_info>
			<added_lines>128,129,130,131,132,133,134,135,136,137,138,139</added_lines>
			<deleted_lines></deleted_lines>
		</method>
		<modified_lines>
			<added_lines>112,113,126,127</added_lines>
			<deleted_lines></deleted_lines>
		</modified_lines>
	</modification>
</commit>
