<commit id='a2b400c72e4069a2ee531a969fa874bef109a763' author='Joshua Z. Zhang' date='2020-08-12 22:47:47-07:00'>
	<dmm_unit complexity='0.6666666666666666' interfacing='0.6666666666666666' size='0.6666666666666666'></dmm_unit>
	<modification change_type='MODIFY' old_name='src\operator\image\image_random-inl.h' new_name='src\operator\image\image_random-inl.h'>
		<file_info nloc='881' complexity='130' token_count='8713'></file_info>
		<method name='mxnet::op::image::FlipImpl' parameters='shape,src,dst'>
				<method_info nloc='17' complexity='7' token_count='220' nesting_level='3' start_line='549' end_line='567'></method_info>
			<added_lines>555,556,557</added_lines>
			<deleted_lines>555</deleted_lines>
		</method>
		<modified_lines>
			<added_lines></added_lines>
			<deleted_lines></deleted_lines>
		</modified_lines>
	</modification>
	<modification change_type='MODIFY' old_name='tests\python\unittest\test_gluon_data_vision.py' new_name='tests\python\unittest\test_gluon_data_vision.py'>
		<file_info nloc='348' complexity='40' token_count='4750'></file_info>
		<method name='test_flip_left_right' parameters=''>
				<method_info nloc='6' complexity='2' token_count='86' nesting_level='0' start_line='196' end_line='201'></method_info>
			<added_lines>197,198,199,200,201</added_lines>
			<deleted_lines>197,198,199,200</deleted_lines>
		</method>
		<method name='test_flip_top_bottom' parameters=''>
				<method_info nloc='6' complexity='2' token_count='86' nesting_level='0' start_line='205' end_line='210'></method_info>
			<added_lines>206,207,208,209,210</added_lines>
			<deleted_lines>205,206,207,208</deleted_lines>
		</method>
		<modified_lines>
			<added_lines></added_lines>
			<deleted_lines>448</deleted_lines>
		</modified_lines>
	</modification>
</commit>
