<commit id='4670eee4f25cef84afca2ba2e2ebf46577968308' author='Tamás Fenyvesi' date='2018-12-14 11:52:33+09:00'>
	<dmm_unit complexity='1.0' interfacing='1.0' size='0.0'></dmm_unit>
	<modification change_type='MODIFY' old_name='nd4j\nd4j-backends\nd4j-api-parent\nd4j-api\src\main\java\org\nd4j\linalg\dataset\api\iterator\KFoldIterator.java' new_name='nd4j\nd4j-backends\nd4j-api-parent\nd4j-api\src\main\java\org\nd4j\linalg\dataset\api\iterator\KFoldIterator.java'>
		<file_info nloc='113' complexity='23' token_count='628'></file_info>
		<method name='KFoldIterator::batch' parameters=''>
				<method_info nloc='3' complexity='1' token_count='18' nesting_level='1' start_line='143' end_line='145'></method_info>
			<added_lines>144</added_lines>
			<deleted_lines></deleted_lines>
		</method>
		<method name='KFoldIterator::totalExamples' parameters=''>
				<method_info nloc='3' complexity='1' token_count='8' nesting_level='1' start_line='97' end_line='99'></method_info>
			<added_lines>98</added_lines>
			<deleted_lines></deleted_lines>
		</method>
		<method name='KFoldIterator::nextFold' parameters=''>
				<method_info nloc='16' complexity='3' token_count='134' nesting_level='1' start_line='178' end_line='196'></method_info>
			<added_lines>178,179,180</added_lines>
			<deleted_lines></deleted_lines>
		</method>
		<method name='KFoldIterator::lastBatch' parameters=''>
				<method_info nloc='3' complexity='1' token_count='8' nesting_level='1' start_line='132' end_line='134'></method_info>
			<added_lines></added_lines>
			<deleted_lines>132,133</deleted_lines>
		</method>
		<method name='KFoldIterator::KFoldIterator' parameters='k,allData'>
				<method_info nloc='19' complexity='4' token_count='138' nesting_level='1' start_line='63' end_line='85'></method_info>
			<added_lines>64,67,68,69,70,71,72,73,74,75,76,77,78,79,80,81,82,83,84</added_lines>
			<deleted_lines>77,78</deleted_lines>
		</method>
		<modified_lines>
			<added_lines>27,28,30,33,34,35,36,37,38,39,40,41,42,45,46,47,48,49,50,51,56,57,58,59,137,138</added_lines>
			<deleted_lines>27,28,32,33,34,35,36,37,38,45,46,47,51,53,54,55,57,58,59,60,61,62,117,123,124,125,126,127,128,129,130,131,167,168,169,170,171,172,173,174,175,176</deleted_lines>
		</modified_lines>
	</modification>
	<modification change_type='MODIFY' old_name='nd4j\nd4j-backends\nd4j-tests\src\test\java\org\nd4j\linalg\dataset\KFoldIteratorTest.java' new_name='nd4j\nd4j-backends\nd4j-tests\src\test\java\org\nd4j\linalg\dataset\KFoldIteratorTest.java'>
		<file_info nloc='175' complexity='25' token_count='1546'></file_info>
		<method name='KFoldIteratorTest::KBatchRandomDataSet::KBatchRandomDataSet' parameters='dataShape,batchSizes'>
				<method_info nloc='27' complexity='4' token_count='246' nesting_level='2' start_line='165' end_line='191'></method_info>
			<added_lines>165,168,169,170,171,172,174,176,177,178,179,180,181,183,184,186,187,190</added_lines>
			<deleted_lines>166,169,172,175,176,179,186,191</deleted_lines>
		</method>
		<method name='KFoldIteratorTest::RandomDataSet::RandomDataSet' parameters='dataShape,ks'>
				<method_info nloc='29' complexity='4' token_count='266' nesting_level='2' start_line='121' end_line='149'></method_info>
			<added_lines>121,122,123,130,131,133,134,135,136,142,143,144,145,146,147,148,149</added_lines>
			<deleted_lines>121,124,125,126,127,128,129,131,132,134,135,136,137,138,139,141,142,144,145,148</deleted_lines>
		</method>
		<method name='KFoldIteratorTest::RandomDataSet::getFoldbutk' parameters='k,feat'>
				<method_info nloc='15' complexity='4' token_count='91' nesting_level='2' start_line='159' end_line='173'></method_info>
			<added_lines>160,161,162,163,164,165,168,169,170,171,172</added_lines>
			<deleted_lines>159,160,162,166,169,172</deleted_lines>
		</method>
		<method name='KFoldIteratorTest::checkCornerCaseException' parameters=''>
				<method_info nloc='6' complexity='1' token_count='71' nesting_level='1' start_line='110' end_line='116'></method_info>
			<added_lines>110,111,112,113,114,115</added_lines>
			<deleted_lines>113,114,115</deleted_lines>
		</method>
		<method name='KFoldIteratorTest::checkCornerCase' parameters=''>
				<method_info nloc='18' complexity='2' token_count='192' nesting_level='1' start_line='119' end_line='140'></method_info>
			<added_lines>119,120,121,122,123,130,131,133,134,135,136</added_lines>
			<deleted_lines>119,121,124,125,126,127,128,129,131,132,134,135,136,137,138,139</deleted_lines>
		</method>
		<method name='KFoldIteratorTest::RandomDataSet::getfoldK' parameters='k,feat'>
				<method_info nloc='3' complexity='2' token_count='23' nesting_level='2' start_line='155' end_line='157'></method_info>
			<added_lines>157</added_lines>
			<deleted_lines>155,156</deleted_lines>
		</method>
		<method name='KFoldIteratorTest::checkFolds' parameters=''>
				<method_info nloc='20' complexity='2' token_count='206' nesting_level='1' start_line='83' end_line='106'></method_info>
			<added_lines>84,85,86,87,94,96,99,100,101,102</added_lines>
			<deleted_lines>83,84,86,89,90,91,98,99,101,102,104</deleted_lines>
		</method>
		<method name='KFoldIteratorTest::checkTestFoldContent' parameters=''>
				<method_info nloc='20' complexity='4' token_count='188' nesting_level='1' start_line='51' end_line='79'></method_info>
			<added_lines>51,52,53,54,55,56,57,58,59,60,61,62,63,64,65,66,67,68,69,70,71,72,73,74,75,76,77,78,79</added_lines>
			<deleted_lines>51,53,56,57,59,63,64,65,66,67,68,69,70,71,72,73,74,76,77,78,79</deleted_lines>
		</method>
		<method name='KFoldIteratorTest::KBatchRandomDataSet::getBatchButK' parameters='k,feat'>
				<method_info nloc='15' complexity='4' token_count='91' nesting_level='2' start_line='211' end_line='225'></method_info>
			<added_lines>211,212,214,218,221,224</added_lines>
			<deleted_lines></deleted_lines>
		</method>
		<method name='KFoldIteratorTest::KBatchRandomDataSet::getAllBatches' parameters=''>
				<method_info nloc='3' complexity='1' token_count='8' nesting_level='2' start_line='193' end_line='195'></method_info>
			<added_lines>193,194</added_lines>
			<deleted_lines>195</deleted_lines>
		</method>
		<method name='KFoldIteratorTest::KBatchRandomDataSet::getBatchK' parameters='k,feat'>
				<method_info nloc='3' complexity='2' token_count='23' nesting_level='2' start_line='202' end_line='204'></method_info>
			<added_lines>202,203</added_lines>
			<deleted_lines></deleted_lines>
		</method>
		<method name='KFoldIteratorTest::test5974' parameters=''>
				<method_info nloc='25' complexity='3' token_count='270' nesting_level='1' start_line='230' end_line='258'></method_info>
			<added_lines>231,232,243,247</added_lines>
			<deleted_lines></deleted_lines>
		</method>
		<method name='KFoldIteratorTest::RandomDataSet::getAllFolds' parameters=''>
				<method_info nloc='3' complexity='1' token_count='8' nesting_level='2' start_line='151' end_line='153'></method_info>
			<added_lines>153</added_lines>
			<deleted_lines>151,152</deleted_lines>
		</method>
		<method name='KFoldIteratorTest::checkCornerCaseA' parameters=''>
				<method_info nloc='17' complexity='2' token_count='180' nesting_level='1' start_line='89' end_line='107'></method_info>
			<added_lines>94,96,99,100,101,102</added_lines>
			<deleted_lines>89,90,91,98,99,101,102,104</deleted_lines>
		</method>
		<modified_lines>
			<added_lines>19,20,32,44,45,46,47,48,49,50,80,81,108,109,154,158,197,198,199,200,201,206,207,208,209,210,227,228</added_lines>
			<deleted_lines>43,44,80,81,82,109,118</deleted_lines>
		</modified_lines>
	</modification>
</commit>
