{"BR": {"BR_id": "20", "BR_author": "volkovmqx", "BRopenT": "2015-10-16T14:14:57Z", "BRcloseT": "2015-10-17T18:19:34Z", "BR_text": {"BRsummary": "getting the wrong person id in the callback", "BRdescription": "\n Hello,\n Any idea what is causing this, AFAIK it's from server.py sending the -1 index instead of 0, in the meantime, the rendered picture is correct, while the detected faces IDs shown in the #peopleInVideo are wrong.\n <denchmark-link:https://camo.githubusercontent.com/01f025cc7612d27e3c0e21d04d92b298ab76cd1280f9dd054a94f5fba49e54d1/687474703a2f2f6937302e696d6775702e6e65742f53637265656e73686f74656563652e706e67></denchmark-link>\n \n \t"}, "comments": {"comments_0": {"comment_id": 1, "comment_author": "volkovmqx", "commentT": "2015-10-16T14:22:35Z", "comment_text": "\n \t\tI think this is being caused by faulty logic in server.py, starting at line 302: \n \n \n openface/demos/web/server.py\n \n \n          Line 302\n       in\n       5ca2354\n \n \n \n \n \n \n  identity = self.svm.predict(rep)[0] if self.svm else -1 \n \n \n \n \n \n \t\t"}, "comments_1": {"comment_id": 2, "comment_author": "volkovmqx", "commentT": "2015-10-16T14:28:28Z", "comment_text": "\n \t\tI'll fix this over the weekend\n \t\t"}}}, "commit": {"commit_id": "85382938042d4d5736b8c58198a3167601d5ec43", "commit_author": "Brandon Amos", "commitT": "2015-10-17 14:19:32-04:00", "commit_complexity": {"commit_NLOC": "0.0", "commit_CCN": "0.0", "commit_Nprams": "0.0"}, "changed_files": {"file_0": {"file_change_type": "MODIFY", "file_Nmethod": 1, "file_old_name": "demos\\web\\server.py", "file_new_name": "demos\\web\\server.py", "file_complexity": {"file_NLOC": "281", "file_CCN": "54", "file_NToken": "2174"}, "hunks": {"hunk_0": {"Ismethod": 1, "added_lines": "302,303,304,305,306,307,308,309,310", "deleted_lines": "302", "method_info": {"method_name": "processFrame", "method_params": "self,dataURL,identity", "method_startline": "249", "method_endline": "351", "method_complexity": {"method_NLOC": "85", "method_CCN": "16", "method_NToken": "658", "method_nesting_level": "1"}}}}}}}}