<bug id='4916' author='edenlightning' open_date='2020-11-30T16:36:40Z' closed_time='2020-12-04T16:28:17Z'>
	<summary>DDP+ manual optimization support</summary>
	<description>
Gradients aren't being synchronised if using manual_backward
	</description>
	<comments>
		<comment id='1' author='edenlightning' date='2020-12-03T17:49:16Z'>
		I was just wondering whether the &lt;denchmark-link:https://github.com/PyTorchLightning/pytorch-lightning/issues/4961&gt;issue&lt;/denchmark-link&gt;
 I've just added is duplicated with this one? Or that is another bug? Thanks!
		</comment>
	</comments>
</bug>