{"BR": {"BR_id": "2428", "BR_author": "raymondlo84", "BRopenT": "2020-09-25T19:24:08Z", "BRcloseT": "2020-10-16T16:02:42Z", "BR_text": {"BRsummary": "[Bug] Build Instruction is missing?", "BRdescription": "\n If you go into the documentation, the \"build instructions\" link is broken.\n <denchmark-link:https://github.com/openvinotoolkit/openvino/blob/master/get-started-linux.md>https://github.com/openvinotoolkit/openvino/blob/master/get-started-linux.md</denchmark-link>\n \n \t"}, "comments": {"comments_0": {"comment_id": 1, "comment_author": "raymondlo84", "commentT": "2020-09-28T12:36:20Z", "comment_text": "\n \t\tHi <denchmark-link:https://github.com/raymondlo84>@raymondlo84</denchmark-link>\n \n It would be great if you can submit a merge request, please see the <denchmark-link:https://github.com/openvinotoolkit/openvino/blob/master/CONTRIBUTING_DOCS.md#edit-existing-document>contributing</denchmark-link>\n  document for guidance.\n This is the correct location for the build instructions: <denchmark-link:https://github.com/openvinotoolkit/openvino/blob/master/build-instruction.md>https://github.com/openvinotoolkit/openvino/blob/master/build-instruction.md</denchmark-link>\n \n Regards,\n Jesus\n \t\t"}}}, "commit": {"commit_id": "595a52ae6782a67b0959d8a593e0dcc5e877d071", "commit_author": "Jesus Espinoza", "commitT": "2020-10-16 19:02:41+03:00", "commit_complexity": {"commit_NLOC": "None", "commit_CCN": "None", "commit_Nprams": "None"}, "changed_files": {"file_0": {"file_change_type": "MODIFY", "file_Nmethod": 0, "file_old_name": "get-started-linux.md", "file_new_name": "get-started-linux.md", "file_complexity": {"file_NLOC": "None", "file_CCN": "None", "file_NToken": "None"}, "hunks": {"hunk_0": {"Ismethod": 0, "added_lines": "15,191,256,267", "deleted_lines": "15,191,256,267"}}}}}}