<commit id='23f6ebf0f3d3932f7226c18c5ff4d81c7278467f' author='Ines Montani' date='2019-02-27 16:37:03+01:00'>
	<dmm_unit complexity='None' interfacing='None' size='None'></dmm_unit>
	<modification change_type='MODIFY' old_name='spacy\lang\uk\lemmatizer.py' new_name='spacy\lang\uk\lemmatizer.py'>
		<file_info nloc='177' complexity='45' token_count='1089'></file_info>
		<method name='__init__' parameters='self'>
				<method_info nloc='12' complexity='3' token_count='52' nesting_level='1' start_line='9' end_line='21'></method_info>
			<added_lines>18</added_lines>
			<deleted_lines>18</deleted_lines>
		</method>
		<modified_lines>
			<added_lines></added_lines>
			<deleted_lines></deleted_lines>
		</modified_lines>
	</modification>
</commit>
