{"BR": {"BR_id": "440", "BR_author": "hmf", "BRopenT": "2020-12-17T09:29:05Z", "BRcloseT": "2020-12-29T00:27:31Z", "BR_text": {"BRsummary": "Documentation error", "BRdescription": "\n <denchmark-h:h2>Description</denchmark-h>\n \n The code example found <denchmark-link:https://docs.djl.ai/model-zoo/index.html#how-to-find-a-pre-trained-model-in-the-model-zoo>here</denchmark-link>\n  is incorrect. The class should be .\n <denchmark-h:h3>Expected Behavior</denchmark-h>\n \n Expected to copy the example, execute it and get a model loaded.\n <denchmark-h:h3>Error Message</denchmark-h>\n \n <denchmark-code>09:24:00.447 [main] DEBUG ai.djl.repository.zoo.ModelZoo - Searching model in zoo provider: ai.djl.basicmodelzoo.BasicZooProvider\n 09:24:00.447 [main] DEBUG ai.djl.repository.zoo.ModelZoo - Searching model in zoo provider: ai.djl.mxnet.zoo.MxZooProvider\n 09:24:00.448 [main] DEBUG ai.djl.repository.zoo.ModelZoo - Searching model in zoo provider: ai.djl.tensorflow.zoo.TfZooProvider\n 09:24:00.448 [main] DEBUG ai.djl.repository.zoo.ModelZoo - Searching model in zoo provider: ai.djl.repository.zoo.DefaultZooProvider\n 09:24:00.448 [main] DEBUG ai.djl.repository.zoo.ModelZoo - No model zoo found in zoo provider: ai.djl.repository.zoo.DefaultZooProvider\n 09:24:00.448 [main] DEBUG ai.djl.repository.zoo.ModelZoo - Checking ModelLoader: cv/image_classification ai.djl.zoo:resnet\n 09:24:00.449 [main] DEBUG ai.djl.repository.zoo.ModelZoo - input/output type found for ModelLoader: CV.IMAGE_CLASSIFICATION null:resnet\n 09:24:00.449 [main] DEBUG ai.djl.repository.zoo.ModelZoo - Checking ModelLoader: cv/image_classification ai.djl.zoo:mlp\n 09:24:00.449 [main] DEBUG ai.djl.repository.zoo.ModelZoo - input/output type found for ModelLoader: CV.IMAGE_CLASSIFICATION null:mlp\n 09:24:00.449 [main] DEBUG ai.djl.repository.zoo.ModelZoo - Checking ModelLoader: cv/object_detection ai.djl.zoo:ssd\n 09:24:00.449 [main] DEBUG ai.djl.repository.zoo.ModelZoo - Checking ModelLoader: cv/object_detection ai.djl.mxnet:ssd\n 09:24:00.449 [main] DEBUG ai.djl.repository.zoo.ModelZoo - Checking ModelLoader: cv/object_detection ai.djl.mxnet:yolo\n 09:24:00.450 [main] DEBUG ai.djl.repository.zoo.ModelZoo - Checking ModelLoader: cv/image_classification ai.djl.mxnet:alexnet\n 09:24:00.450 [main] DEBUG ai.djl.repository.zoo.ModelZoo - input/output type found for ModelLoader: CV.IMAGE_CLASSIFICATION null:alexnet\n 09:24:00.450 [main] DEBUG ai.djl.repository.zoo.ModelZoo - Checking ModelLoader: cv/image_classification ai.djl.mxnet:darknet\n 09:24:00.450 [main] DEBUG ai.djl.repository.zoo.ModelZoo - input/output type found for ModelLoader: CV.IMAGE_CLASSIFICATION null:darknet\n 09:24:00.450 [main] DEBUG ai.djl.repository.zoo.ModelZoo - Checking ModelLoader: cv/image_classification ai.djl.mxnet:densenet\n 09:24:00.450 [main] DEBUG ai.djl.repository.zoo.ModelZoo - input/output type found for ModelLoader: CV.IMAGE_CLASSIFICATION null:densenet\n 09:24:00.450 [main] DEBUG ai.djl.repository.zoo.ModelZoo - Checking ModelLoader: cv/image_classification ai.djl.mxnet:googlenet\n 09:24:00.450 [main] DEBUG ai.djl.repository.zoo.ModelZoo - input/output type found for ModelLoader: CV.IMAGE_CLASSIFICATION null:googlenet\n 09:24:00.451 [main] DEBUG ai.djl.repository.zoo.ModelZoo - Checking ModelLoader: cv/image_classification ai.djl.mxnet:inceptionv3\n 09:24:00.451 [main] DEBUG ai.djl.repository.zoo.ModelZoo - input/output type found for ModelLoader: CV.IMAGE_CLASSIFICATION null:inceptionv3\n 09:24:00.451 [main] DEBUG ai.djl.repository.zoo.ModelZoo - Checking ModelLoader: cv/image_classification ai.djl.mxnet:mlp\n 09:24:00.451 [main] DEBUG ai.djl.repository.zoo.ModelZoo - input/output type found for ModelLoader: CV.IMAGE_CLASSIFICATION null:mlp\n 09:24:00.451 [main] DEBUG ai.djl.repository.zoo.ModelZoo - Checking ModelLoader: cv/image_classification ai.djl.mxnet:mobilenet\n 09:24:00.451 [main] DEBUG ai.djl.repository.zoo.ModelZoo - input/output type found for ModelLoader: CV.IMAGE_CLASSIFICATION null:mobilenet\n 09:24:00.451 [main] DEBUG ai.djl.repository.zoo.ModelZoo - Checking ModelLoader: cv/image_classification ai.djl.mxnet:resnest\n 09:24:00.452 [main] DEBUG ai.djl.repository.zoo.ModelZoo - input/output type found for ModelLoader: CV.IMAGE_CLASSIFICATION null:resnest\n 09:24:00.452 [main] DEBUG ai.djl.repository.zoo.ModelZoo - Checking ModelLoader: cv/image_classification ai.djl.mxnet:resnet\n 09:24:00.452 [main] DEBUG ai.djl.repository.zoo.ModelZoo - input/output type found for ModelLoader: CV.IMAGE_CLASSIFICATION null:resnet\n 09:24:00.452 [main] DEBUG ai.djl.repository.zoo.ModelZoo - Checking ModelLoader: cv/image_classification ai.djl.mxnet:resnext\n 09:24:00.452 [main] DEBUG ai.djl.repository.zoo.ModelZoo - input/output type found for ModelLoader: CV.IMAGE_CLASSIFICATION null:resnext\n 09:24:00.452 [main] DEBUG ai.djl.repository.zoo.ModelZoo - Checking ModelLoader: cv/image_classification ai.djl.mxnet:senet\n 09:24:00.453 [main] DEBUG ai.djl.repository.zoo.ModelZoo - input/output type found for ModelLoader: CV.IMAGE_CLASSIFICATION null:senet\n 09:24:00.453 [main] DEBUG ai.djl.repository.zoo.ModelZoo - Checking ModelLoader: cv/image_classification ai.djl.mxnet:se_resnext\n 09:24:00.453 [main] DEBUG ai.djl.repository.zoo.ModelZoo - input/output type found for ModelLoader: CV.IMAGE_CLASSIFICATION null:se_resnext\n 09:24:00.453 [main] DEBUG ai.djl.repository.zoo.ModelZoo - Checking ModelLoader: cv/image_classification ai.djl.mxnet:squeezenet\n 09:24:00.453 [main] DEBUG ai.djl.repository.zoo.ModelZoo - input/output type found for ModelLoader: CV.IMAGE_CLASSIFICATION null:squeezenet\n 09:24:00.454 [main] DEBUG ai.djl.repository.zoo.ModelZoo - Checking ModelLoader: cv/image_classification ai.djl.mxnet:vgg\n 09:24:00.454 [main] DEBUG ai.djl.repository.zoo.ModelZoo - input/output type found for ModelLoader: CV.IMAGE_CLASSIFICATION null:vgg\n 09:24:00.454 [main] DEBUG ai.djl.repository.zoo.ModelZoo - Checking ModelLoader: cv/image_classification ai.djl.mxnet:xception\n 09:24:00.454 [main] DEBUG ai.djl.repository.zoo.ModelZoo - input/output type found for ModelLoader: CV.IMAGE_CLASSIFICATION null:xception\n 09:24:00.454 [main] DEBUG ai.djl.repository.zoo.ModelZoo - Checking ModelLoader: cv/pose_estimation ai.djl.mxnet:simple_pose\n 09:24:00.454 [main] DEBUG ai.djl.repository.zoo.ModelZoo - Checking ModelLoader: cv/instance_segmentation ai.djl.mxnet:mask_rcnn\n 09:24:00.454 [main] DEBUG ai.djl.repository.zoo.ModelZoo - Checking ModelLoader: cv/action_recognition ai.djl.mxnet:action_recognition\n 09:24:00.454 [main] DEBUG ai.djl.repository.zoo.ModelZoo - Checking ModelLoader: nlp/question_answer ai.djl.mxnet:bertqa\n 09:24:00.455 [main] DEBUG ai.djl.repository.zoo.ModelZoo - Checking ModelLoader: nlp/word_embedding ai.djl.mxnet:glove\n 09:24:00.455 [main] DEBUG ai.djl.repository.zoo.ModelZoo - Checking ModelLoader: cv/image_classification ai.djl.tensorflow:resnet\n 09:24:00.455 [main] DEBUG ai.djl.repository.zoo.ModelZoo - input/output type found for ModelLoader: CV.IMAGE_CLASSIFICATION null:resnet\n 09:24:00.455 [main] DEBUG ai.djl.repository.zoo.ModelZoo - Checking ModelLoader: cv/image_classification ai.djl.tensorflow:mobilenet\n 09:24:00.455 [main] DEBUG ai.djl.repository.zoo.ModelZoo - input/output type found for ModelLoader: CV.IMAGE_CLASSIFICATION null:mobilenet\n 09:24:00.455 [main] DEBUG ai.djl.repository.zoo.ModelZoo - Checking ModelLoader: cv/object_detection ai.djl.tensorflow:ssd\n Exception in thread \"main\" ai.djl.repository.zoo.ModelNotFoundException: No matching model with specified Input/Output type found.\n \tat ai.djl.repository.zoo.ModelZoo.loadModel(ModelZoo.java:173)\n \tat examples.djl.LoadModelZoo$.main(LoadModelZoo.scala:233)\n \tat examples.djl.LoadModelZoo.main(LoadModelZoo.scala)\n \n </denchmark-code>\n \n <denchmark-h:h2>How to Reproduce?</denchmark-h>\n \n Run the code example as is.\n <denchmark-h:h3>Steps to reproduce</denchmark-h>\n \n \n Copy & paste the example\n Adapted to Scala (see code below)\n Execute\n \n     val criteria = Criteria.builder()\n      .optApplication(Application.CV.IMAGE_CLASSIFICATION)\n       .setTypes(classOf[Image], classOf[Classification])\n       .optFilter(\"layers\", \"50\")\n       .optFilter(\"flavor\", \"v1\")\n       .optFilter(\"dataset\", \"cifar10\")\n       .build()\n \n     val ssd = ModelZoo.loadModel(criteria)\n <denchmark-h:h2>What have you tried to solve it?</denchmark-h>\n \n To solve it, the class type must be changed as follows:\n     val criteria: Criteria[Image, Classifications] = Criteria.builder()\n       .optApplication(Application.CV.IMAGE_CLASSIFICATION)\n       .setTypes(classOf[Image], classOf[Classifications])\n       .optFilter(\"layers\", \"50\")\n       .optFilter(\"flavor\", \"v1\")\n       .optFilter(\"dataset\", \"cifar10\")\n       .build()\n \n     val ssd: ZooModel[Image, Classifications] = ModelZoo.loadModel(criteria)\n <denchmark-h:h2>Environment Info</denchmark-h>\n \n I execute this in a Scala project (JDK11,  Scala 3 (M2), Mill build tool, Linux)\n \t"}, "comments": {"comments_0": {"comment_id": 1, "comment_author": "hmf", "commentT": "2020-12-22T16:08:44Z", "comment_text": "\n \t\t<denchmark-link:https://github.com/hmf>@hmf</denchmark-link>\n  Please feel free to raise a PR to fix it\n \t\t"}, "comments_1": {"comment_id": 2, "comment_author": "hmf", "commentT": "2020-12-29T00:27:31Z", "comment_text": "\n \t\tthe doc has been fixed\n \t\t"}}}, "commit": {"commit_id": "79250c4d75624ec572ed71b153a312aeefcfb3e5", "commit_author": "Frank Liu", "commitT": "2020-12-28 14:16:59-08:00", "changed_files": {"file_0": {"file_change_type": "MODIFY", "file_Nmethod": 0, "file_old_name": "model-zoo\\README.md", "file_new_name": "model-zoo\\README.md", "hunks": {"hunk_0": {"Ismethod": 0, "added_lines": "55,58,64,75", "deleted_lines": "55,58,64,75"}}}, "file_1": {"file_change_type": "MODIFY", "file_Nmethod": 0, "file_old_name": "mxnet\\mxnet-model-zoo\\README.md", "file_new_name": "mxnet\\mxnet-model-zoo\\README.md", "hunks": {"hunk_0": {"Ismethod": 0, "added_lines": "65,66", "deleted_lines": "65,66"}}}}}}