{"BR": {"BR_id": "240", "BR_author": "fritzo", "BRopenT": "2017-10-11T20:50:37Z", "BRcloseT": "2017-10-11T23:07:13Z", "BR_text": {"BRsummary": "make docs is broken", "BRdescription": "\n Now I can't build docs. It would be nice if we could avoid treating warnings as errors locally.\n <denchmark-code>$ make docs\n /Library/Developer/CommandLineTools/usr/bin/make -C docs html\n Running Sphinx v1.6.3\n loading intersphinx inventory from https://docs.python.org/objects.inv...\n intersphinx inventory has moved: https://docs.python.org/objects.inv -> https://docs.python.org/2/objects.inv\n building [mo]: targets for 0 po files that are out of date\n building [html]: targets for 9 source files that are out of date\n updating environment: 9 added, 0 changed, 0 removed\n reading sources... [100%] primitives\n \n Warning, treated as error:\n /Users/fritzobermeyer/github/uber/pyro/pyro/distributions/transformed_distribution.py:docstring of pyro.distributions.transformed_distribution.TransformedDistribution:1:Inline interpreted text or phrase reference start-string without end-string.\n make[1]: *** [html] Error 1\n make: *** [docs] Error 2\n </denchmark-code>\n \n \t"}, "comments": {}}, "commit": {"commit_id": "8674edb2ea4cfa907da330b11fff02ccefdcb683", "commit_author": "Neeraj Pradhan", "commitT": "2017-10-11 16:07:12-07:00", "changed_files": {"file_0": {"file_change_type": "MODIFY", "file_Nmethod": 0, "file_old_name": "docs\\Makefile", "file_new_name": "docs\\Makefile", "hunks": {"hunk_0": {"Ismethod": 0, "added_lines": "5", "deleted_lines": "5"}}}}}}