<commit id='5d45992c841e531204282988392810b046c26786' author='Lalit Pagaria' date='2020-11-02 15:18:43+01:00'>
	<dmm_unit complexity='None' interfacing='None' size='None'></dmm_unit>
	<modification change_type='MODIFY' old_name='haystack\document_store\elasticsearch.py' new_name='haystack\document_store\elasticsearch.py'>
		<file_info nloc='419' complexity='79' token_count='3162'></file_info>
		<method name='update_document_meta' parameters='self,str,str'>
				<method_info nloc='3' complexity='1' token_count='51' nesting_level='1' start_line='305' end_line='307'></method_info>
			<added_lines>307</added_lines>
			<deleted_lines>307</deleted_lines>
		</method>
		<modified_lines>
			<added_lines></added_lines>
			<deleted_lines></deleted_lines>
		</modified_lines>
	</modification>
	<modification change_type='MODIFY' old_name='haystack\preprocessor\utils.py' new_name='haystack\preprocessor\utils.py'>
		<file_info nloc='212' complexity='33' token_count='1348'></file_info>
		<modified_lines>
			<added_lines>199,200,204,205,206</added_lines>
			<deleted_lines>199,203,204</deleted_lines>
		</modified_lines>
	</modification>
	<modification change_type='MODIFY' old_name='haystack\reader\farm.py' new_name='haystack\reader\farm.py'>
		<file_info nloc='364' complexity='27' token_count='2402'></file_info>
		<method name='predict' parameters='self,str,None'>
				<method_info nloc='15' complexity='2' token_count='115' nesting_level='1' start_line='305' end_line='351'></method_info>
			<added_lines>341</added_lines>
			<deleted_lines></deleted_lines>
		</method>
		<modified_lines>
			<added_lines></added_lines>
			<deleted_lines></deleted_lines>
		</modified_lines>
	</modification>
	<modification change_type='MODIFY' old_name='haystack\retriever\dense.py' new_name='haystack\retriever\dense.py'>
		<file_info nloc='267' complexity='34' token_count='1856'></file_info>
		<method name='embed' parameters='self'>
				<method_info nloc='17' complexity='8' token_count='124' nesting_level='1' start_line='359' end_line='382'></method_info>
			<added_lines>373,374</added_lines>
			<deleted_lines></deleted_lines>
		</method>
		<modified_lines>
			<added_lines></added_lines>
			<deleted_lines>8,9,12,14</deleted_lines>
		</modified_lines>
	</modification>
</commit>
