{"BR": {"BR_id": "269", "BR_author": "esimov", "BRopenT": "2018-08-10T13:11:41Z", "BRcloseT": "2018-08-29T17:14:14Z", "BR_text": {"BRsummary": "gocv.NormMixMax should be gocv.NormMinMax", "BRdescription": "\n This is actually not an issue, but a notice that gocv.NormMixMax const in fact should be gocv.NormMinMax to get aligned with the standard OpenCV NORM_MINMAX enum type.\n Here is the reference for it: <denchmark-link:https://docs.opencv.org/master/d2/de8/group__core__array.html#gad12cefbcb5291cf958a85b4b67b6149f>https://docs.opencv.org/master/d2/de8/group__core__array.html#gad12cefbcb5291cf958a85b4b67b6149f</denchmark-link>\n \n It's just a bit confusing.\n \t"}, "comments": {"comments_0": {"comment_id": 1, "comment_author": "esimov", "commentT": "2018-08-13T08:17:24Z", "comment_text": "\n \t\tThat looks like a typo bug to me. Thanks for pointing that out, <denchmark-link:https://github.com/esimov>@esimov</denchmark-link>\n \n \t\t"}, "comments_1": {"comment_id": 2, "comment_author": "esimov", "commentT": "2018-08-24T09:17:50Z", "comment_text": "\n \t\tThis has been corrected in the dev branch. I will close this issue on next release.\n \t\t"}, "comments_2": {"comment_id": 3, "comment_author": "esimov", "commentT": "2018-08-24T10:52:38Z", "comment_text": "\n \t\t<denchmark-link:https://github.com/deadprogram>@deadprogram</denchmark-link>\n  great, thank you.\n \t\t"}, "comments_3": {"comment_id": 4, "comment_author": "esimov", "commentT": "2018-08-29T17:14:14Z", "comment_text": "\n \t\tThis has been released as part of v0.16.0 thank you.\n \t\t"}}}, "commit": {"commit_id": "2a1087857b3cdf3c76257b500219e894a5c9075b", "commit_author": "Ron Evans", "commitT": "2018-08-24 11:17:06+02:00", "changed_files": {"file_0": {"file_change_type": "MODIFY", "file_Nmethod": 0, "file_old_name": "core.go", "file_new_name": "core.go", "hunks": {"hunk_0": {"Ismethod": 0, "added_lines": "1353,1354", "deleted_lines": "1353,1354"}}}, "file_1": {"file_change_type": "MODIFY", "file_Nmethod": 1, "file_old_name": "core_test.go", "file_new_name": "core_test.go", "hunks": {"hunk_0": {"Ismethod": 1, "added_lines": "912", "deleted_lines": "912", "method_info": {"method_name": "TestMatNormalize", "method_params": "T", "method_startline": "909", "method_endline": "916"}}}}}}}