<bug_data>
<bug id='17875' author='leezu' open_date='2020-03-19T20:18:39Z' closed_time='2020-03-23T18:25:42Z'>
 	<summary>USE_TVM_OP=1 build broken with DMLC_LOG_FATAL_THROW=0</summary>
 	<description>
 &lt;denchmark-h:h2&gt;Description&lt;/denchmark-h&gt;
 
 Setting -DDMLC_LOG_FATAL_THROW=0 is useful for debugging with gdb or lldb. Unfortunately we can't compile MXNet with USE_TVM_OP=1 in that case.
 &lt;denchmark-h:h3&gt;Error Message&lt;/denchmark-h&gt;
 
 &lt;denchmark-code&gt;[658/658] Linking CXX shared library libmxnet.so
 FAILED: libmxnet.so
 : &amp;&amp; /usr/bin/c++ -fPIC -Wall -Wno-sign-compare -O3 -std=c++11 -fopenmp   -shared -Wl,-soname,libmxnet.so -o libmxnet.so CMakeFiles/mxnet.dir/dummy.c.o -L/home/ubuntu/src/mxnet-master/build/3rdparty/tvm -Wl,-rpath,/usr/local/lib:/home/ubuntu/src/mxnet-master/build/3rdparty/tvm:  -Wl,--whole-archive  libmxnet.a  -Wl,--no-whole-archive  libmxnet.a  3rdparty/dmlc-core/libdmlc.a  -ldl  3rdparty/mkldnn/src/libdnnl.a  -lpthread  -Wl,--start-group  /opt/intel/mkl/lib/intel64/libmkl_intel_lp64.a  /opt/intel/mkl/lib/intel64/libmkl_intel_thread.a  /opt/intel/mkl/lib/intel64/libmkl_core.a  /usr/local/lib/libiomp5.so  -Wl,--end-group  /usr/lib/x86_64-linux-gnu/librt.so  /usr/lib/x86_64-linux-gnu/libopencv_highgui.so.3.2.0  /usr/lib/x86_64-linux-gnu/libopencv_imgcodecs.so.3.2.0  /usr/lib/x86_64-linux-gnu/libopencv_imgproc.so.3.2.0  /usr/lib/x86_64-linux-gnu/libopencv_core.so.3.2.0  -llapack  -ltvm_runtime  /usr/lib/gcc/x86_64-linux-gnu/7/libgomp.so  -lpthread  -lrt &amp;&amp; cd /home/ubuntu/src/mxnet-master/build &amp;&amp; /home/ubuntu/.pyenv/versions/3.8.2-debug/lib/python3.8/site-packages/cmake/data/bin/cmake -E copy /home/ubuntu/src/mxnet-master/build/3rdparty/mkldnn/include/dnnl_config.h /home/ubuntu/src/mxnet-master/include/mkldnn/ &amp;&amp; /home/ubuntu/.pyenv/versions/3.8.2-debug/lib/python3.8/site-packages/cmake/data/bin/cmake -E copy /home/ubuntu/src/mxnet-master/build/3rdparty/mkldnn/include/dnnl_version.h /home/ubuntu/src/mxnet-master/include/mkldnn/ &amp;&amp; cd /home/ubuntu/src/mxnet-master/build &amp;&amp; /home/ubuntu/.pyenv/versions/3.8.2-debug/lib/python3.8/site-packages/cmake/data/bin/cmake -E env PYTHONPATH="/home/ubuntu/src/mxnet-master/3rdparty/tvm/python:/home/ubuntu/src/mxnet-master/3rdparty/tvm/topi/python:/home/ubuntu/src/mxnet-master/contrib" LD_LIBRARY_PATH=/home/ubuntu/src/mxnet-master/build:/home/ubuntu/src/mxnet-master/build/3rdparty/tvm:/usr/local/cuda/lib64:/usr/local/lib:/usr/lib:/usr/local/cuda/extras/CUPTI/lib64:/usr/local/mpi/lib:/home/ubuntu/local/lib:/home/ubuntu/local/lib:/usr/local/cuda/lib64:/usr/local/lib:/usr/lib:/usr/local/cuda/extras/CUPTI/lib64:/usr/local/mpi/lib:/home/ubuntu/local/lib /home/ubuntu/.pyenv/versions/3.8.2-debug/bin/python3.8 /home/ubuntu/src/mxnet-master/contrib/tvmop/compile.py -o/home/ubuntu/src/mxnet-master/build --config /home/ubuntu/src/mxnet-master/build/tvmop.conf -L /home/ubuntu/src/mxnet-master/build/3rdparty/tvm
 [19:56:21] ../3rdparty/tvm/src/node/reflection.cc:113: AttributeError: Variable object has no attributed shape
 
 Child aborted
 ninja: build stopped: subcommand failed.
 &lt;/denchmark-code&gt;
 
 &lt;denchmark-h:h2&gt;To Reproduce&lt;/denchmark-h&gt;
 
 &lt;denchmark-h:h3&gt;Steps to reproduce&lt;/denchmark-h&gt;
 
 
 Apply patch below
 Compile with cmake -GNinja -DUSE_CUDA=0 -DUSE_TVM_OP=ON ..; ninja
 
 diff --git a/CMakeLists.txt b/CMakeLists.txt
 index 365da2d90..b4c9d267b 100644
 --- a/CMakeLists.txt
 +++ b/CMakeLists.txt
 @@ -151,7 +151,7 @@ endif()
  add_definitions(-DDMLC_MODERN_THREAD_LOCAL=0)
  # disable stack trace in exception by default.
  add_definitions(-DDMLC_LOG_STACK_TRACE_SIZE=0)
 -add_definitions(-DDMLC_LOG_FATAL_THROW=1)
 +add_definitions(-DDMLC_LOG_FATAL_THROW=0)
 
  if(MSVC)
    add_definitions(-DWIN32_LEAN_AND_MEAN)
 	</description>
 	<comments>
 		<comment id='1' author='leezu' date='2020-03-20T00:30:18Z'>
 		This failure is from tvmop/compile.py. Backtrace:
 &lt;denchmark-code&gt;frame #2: 0x00007fff4cc3a496 libtvm.so`dmlc::LogMessageFatal::~LogMessageFatal() + 166                                                                                                 frame #3: 0x00007fff4cdbf0cd libtvm.so`tvm::ReflectionVTable::GetAttr(tvm::runtime::Object*, std::__cxx11::basic_string&lt;char, std::char_traits&lt;char&gt;, std::allocator&lt;char&gt; &gt; const&amp;
 ) const + 605                                                                                                                                                                              frame #4: 0x00007fff4cdbf79e libtvm.so`tvm::NodeGetAttr(tvm::runtime::TVMArgs, tvm::runtime::TVMRetValue*) + 766
     frame #5: 0x00007fff4cdc0d84 libtvm.so`std::_Function_handler&lt;void (tvm::runtime::TVMArgs, tvm::runtime::TVMRetValue*), void (*)(tvm::runtime::TVMArgs, tvm::runtime::TVMRetValue*)&gt;::_M_invoke(std::_Any_data const&amp;, tvm::runtime::TVMArgs&amp;&amp;, tvm::runtime::TVMRetValue*&amp;&amp;) + 20
     frame #6: 0x00007fff4d49c75e libtvm.so`TVMFuncCall + 110
     frame #7: 0x00007ffff5965dae libffi.so.6`ffi_call_unix64 + 76
     frame #8: 0x00007ffff596571f libffi.so.6`ffi_call + 559
 &lt;/denchmark-code&gt;
 
 		</comment>
 	</comments>
 </bug>
<commit id='3840786a25b16d0cfe6411e26f25aba8d3b574ff' author='Leonard Lausen' date='2020-03-23 11:25:26-07:00'>
 	<dmm_unit complexity='None' interfacing='None' size='None'></dmm_unit>
 	<modification change_type='MODIFY' old_name='CMakeLists.txt' new_name='CMakeLists.txt'>
 		<file_info nloc='None' complexity='None' token_count='None'></file_info>
 		<modified_lines>
 			<added_lines>74,696,714,715,716,717,718,719,720,721,722,723,725,726,727,728,730,731,732,733,734,735,736,737,738,739,740,741,742,743,744,745,746,747,750,751,752,753,754,755,756,759</added_lines>
 			<deleted_lines>154,713,714,715,716,717,718,719,720,721,722,723,724,725,726,727,728,729,730,731,732,733,734,735,736,737,738,739,740,741,742,743,744,745,746,747,748,750,751,753,754,755,756,757,760,765</deleted_lines>
 		</modified_lines>
 	</modification>
 	<modification change_type='MODIFY' old_name='cmake\BuildTVM.cmake' new_name='cmake\BuildTVM.cmake'>
 		<file_info nloc='None' complexity='None' token_count='None'></file_info>
 		<modified_lines>
 			<added_lines>142,143,144,145,146</added_lines>
 			<deleted_lines>140,141,142</deleted_lines>
 		</modified_lines>
 	</modification>
 </commit>
</bug_data>
