<commit id='06eba7fdf11c6d84bf127ffbc7b9349eda5eb825' author='Guillaume Klein' date='2018-11-28 13:18:27+01:00'>
	<dmm_unit complexity='None' interfacing='None' size='None'></dmm_unit>
	<modification change_type='MODIFY' old_name='CHANGELOG.md' new_name='CHANGELOG.md'>
		<file_info nloc='None' complexity='None' token_count='None'></file_info>
		<modified_lines>
			<added_lines>20</added_lines>
			<deleted_lines></deleted_lines>
		</modified_lines>
	</modification>
	<modification change_type='MODIFY' old_name='opennmt\models\sequence_to_sequence.py' new_name='opennmt\models\sequence_to_sequence.py'>
		<file_info nloc='338' complexity='46' token_count='2304'></file_info>
		<method name='_build' parameters='self,features,labels,params,mode,config'>
				<method_info nloc='120' complexity='12' token_count='810' nesting_level='1' start_line='179' end_line='312'></method_info>
			<added_lines>239</added_lines>
			<deleted_lines>239</deleted_lines>
		</method>
		<modified_lines>
			<added_lines></added_lines>
			<deleted_lines></deleted_lines>
		</modified_lines>
	</modification>
</commit>
