{"BR": {"BR_id": "222", "BR_author": "chewxy", "BRopenT": "2018-07-31T04:46:24Z", "BRcloseT": "2019-08-26T06:28:59Z", "BR_text": {"BRsummary": "Machine hangs when allocating more CUDA memory than possible", "BRdescription": "\n v0.9.0-working branch\n \t"}, "comments": {"comments_0": {"comment_id": 1, "comment_author": "chewxy", "commentT": "2019-08-26T06:28:59Z", "comment_text": "\n \t\tSeems to be fixed now\n \t\t"}}}, "commit": {"commit_id": "9f42d7fbc41e3d0cc76c5bf882f5ca0de3cc1d69", "commit_author": "chewxy", "commitT": "2018-08-11 02:54:46+00:00", "changed_files": {"file_0": {"file_change_type": "MODIFY", "file_Nmethod": 1, "file_old_name": "cuda\\external.go", "file_new_name": "cuda\\external.go", "hunks": {"hunk_0": {"Ismethod": 1, "added_lines": "140,153,154", "deleted_lines": "152,153", "method_info": {"method_name": "doInit", "method_params": "int64", "method_startline": "105", "method_endline": "163"}}}}}}}