<commit id='b0c7717f867468d00a4baa58be5f6daad777f4ee' author='Aseem Wadhwa' date='2019-12-11 09:43:08+05:18'>
	<dmm_unit complexity='None' interfacing='None' size='None'></dmm_unit>
	<modification change_type='MODIFY' old_name='docs\NeuralNetworkGuide.md' new_name='docs\NeuralNetworkGuide.md'>
		<file_info nloc='None' complexity='None' token_count='None'></file_info>
		<modified_lines>
			<added_lines>269,272,273,274,275,278,279,282,298,300,301,302,303,304,307,308</added_lines>
			<deleted_lines>269,270,272,276,277,295,296,298,301,302</deleted_lines>
		</modified_lines>
	</modification>
	<modification change_type='MODIFY' old_name='examples\neural_network_inference\tensorflow_converter\Tensorflow_2\tf_keras_fashion_mnist.ipynb' new_name='examples\neural_network_inference\tensorflow_converter\Tensorflow_2\tf_keras_fashion_mnist.ipynb'>
		<file_info nloc='None' complexity='None' token_count='None'></file_info>
		<modified_lines>
			<added_lines>186,187,188,189,190,193,194</added_lines>
			<deleted_lines>188,189</deleted_lines>
		</modified_lines>
	</modification>
</commit>
