{"BR": {"BR_id": "1426", "BR_author": "vfdev-5", "BRopenT": "2020-10-31T12:16:33Z", "BRcloseT": "2020-11-05T14:07:42Z", "BR_text": {"BRsummary": "GitHub CI on Windows is broken.", "BRdescription": "\n <denchmark-h:h2>\ud83d\udc1b Bug description</denchmark-h>\n \n <denchmark-link:https://github.com/pytorch/ignite/pull/1425/checks?check_run_id=1335601277#step:6:39>https://github.com/pytorch/ignite/pull/1425/checks?check_run_id=1335601277#step:6:39</denchmark-link>\n \n Normally, we should skip distributed tests on windows with SKIP_DISTRIB_TESTS=1 CI_PYTHON_VERSION=\"3.7\" sh tests/run_cpu_tests.sh but a distributed test was executed:\n <denchmark-code>tests/ignite/contrib/engines/test_common.py::test_distrib_cpu ERROR      [  2%]\n </denchmark-code>\n \n \t"}, "comments": {"comments_0": {"comment_id": 1, "comment_author": "vfdev-5", "commentT": "2020-11-01T16:52:04Z", "comment_text": "\n \t\tRelated to beta support of distibuted on windows in pytorch 1.7\n <denchmark-link:https://pytorch.org/docs/master/distributed.html#backends-that-come-with-pytorch>https://pytorch.org/docs/master/distributed.html#backends-that-come-with-pytorch</denchmark-link>\n \n \t\t"}}}, "commit": {"commit_id": "7a222b393db6c2f02327038cb05ce95e13ca8f26", "commit_author": "vfdev", "commitT": "2020-11-05 15:07:41+01:00", "changed_files": {"file_0": {"file_change_type": "MODIFY", "file_Nmethod": 0, "file_old_name": ".circleci\\config.yml", "file_new_name": ".circleci\\config.yml", "hunks": {"hunk_0": {"Ismethod": 0, "added_lines": "107,166,259", "deleted_lines": "107,166,259"}}}, "file_1": {"file_change_type": "MODIFY", "file_Nmethod": 0, "file_old_name": ".github\\workflows\\hvd-tests.yml", "file_new_name": ".github\\workflows\\hvd-tests.yml", "hunks": {"hunk_0": {"Ismethod": 0, "added_lines": "51", "deleted_lines": "51"}}}, "file_2": {"file_change_type": "MODIFY", "file_Nmethod": 0, "file_old_name": ".github\\workflows\\tpu-tests.yml", "file_new_name": ".github\\workflows\\tpu-tests.yml", "hunks": {"hunk_0": {"Ismethod": 0, "added_lines": "69", "deleted_lines": "69"}}}, "file_3": {"file_change_type": "MODIFY", "file_Nmethod": 0, "file_old_name": ".github\\workflows\\unittests.yml", "file_new_name": ".github\\workflows\\unittests.yml", "hunks": {"hunk_0": {"Ismethod": 0, "added_lines": "73", "deleted_lines": "73"}}}, "file_4": {"file_change_type": "MODIFY", "file_Nmethod": 0, "file_old_name": ".travis.yml", "file_new_name": ".travis.yml", "hunks": {"hunk_0": {"Ismethod": 0, "added_lines": "46", "deleted_lines": "46"}}}, "file_5": {"file_change_type": "MODIFY", "file_Nmethod": 0, "file_old_name": "CONTRIBUTING.md", "file_new_name": "CONTRIBUTING.md", "hunks": {"hunk_0": {"Ismethod": 0, "added_lines": "149,151", "deleted_lines": "149,151"}}}, "file_6": {"file_change_type": "MODIFY", "file_Nmethod": 1, "file_old_name": "tests\\ignite\\conftest.py", "file_new_name": "tests\\ignite\\conftest.py", "hunks": {"hunk_0": {"Ismethod": 1, "added_lines": "111,112,113,114,115,116,121,126,127", "deleted_lines": "114", "method_info": {"method_name": "distributed_context_single_node_gloo", "method_params": "local_rank,world_size", "method_startline": "107", "method_endline": "127"}}}}, "file_7": {"file_change_type": "MODIFY", "file_Nmethod": 0, "file_old_name": "tests\\ignite\\contrib\\handlers\\test_tqdm_logger.py", "file_new_name": "tests\\ignite\\contrib\\handlers\\test_tqdm_logger.py", "hunks": {"hunk_0": {"Ismethod": 0, "added_lines": "16", "deleted_lines": "16"}}}, "file_8": {"file_change_type": "MODIFY", "file_Nmethod": 0, "file_old_name": "tests\\run_cpu_tests.sh", "file_new_name": "tests\\run_cpu_tests.sh", "hunks": {"hunk_0": {"Ismethod": 0, "added_lines": "5,6,7,8,9,10,11,20", "deleted_lines": "5"}}}}}}