{"BR": {"BR_id": "168", "BR_author": "Timoeller", "BRopenT": "2020-06-22T17:06:42Z", "BRcloseT": "2020-06-23T14:49:33Z", "BR_text": {"BRsummary": "FARMReader return multiple is_impossible answers to one question", "BRdescription": "\n We need to adjust to the new format introduced in FARM 0.4.4\n \t"}, "comments": {"comments_0": {"comment_id": 1, "comment_author": "Timoeller", "commentT": "2020-06-23T13:14:38Z", "comment_text": "\n \t\tThe issue seems to be coming from two place. One is within FARM the other is how haystack handles results coming back from FARM.\n We will create separate PRs to fix both and release a newer version of FARM asap.\n \t\t"}}}, "commit": {"commit_id": "5852cbd306039d0f24b528583e587d46144d09bd", "commit_author": "Timo Moeller", "commitT": "2020-06-23 16:49:32+02:00", "changed_files": {"file_0": {"file_change_type": "MODIFY", "file_Nmethod": 2, "file_old_name": "haystack\\reader\\farm.py", "file_new_name": "haystack\\reader\\farm.py", "hunks": {"hunk_0": {"Ismethod": 1, "added_lines": "258,259,260", "deleted_lines": "258", "method_info": {"method_name": "predict", "method_params": "self,str,None", "method_startline": "207", "method_endline": "292"}}, "hunk_1": {"Ismethod": 1, "added_lines": "412,413,414,415,416,417,418,419,420,421", "deleted_lines": null, "method_info": {"method_name": "_check_no_answer", "method_params": "dict", "method_startline": "412", "method_endline": "421"}}}}}}}