{"BR": {"BR_id": "3982", "BR_author": "marload", "BRopenT": "2020-08-11T02:07:13Z", "BRcloseT": "2020-08-22T05:34:34Z", "BR_text": {"BRsummary": "Return invalid dtype when MPC is applied to Other Dtype Tensor", "BRdescription": "\n <denchmark-h:h2>Description</denchmark-h>\n \n When MPC is applied to the int tensor, it must be int but float return.\n <denchmark-h:h2>How to Reproduce</denchmark-h>\n \n x = torch.tensor([1, 2, 3])\n print(x.dtype) # torch.int64\n \n x = share(bob, alice, crypto_provider=theo)\n print(x.dtype) # torch.float32 # should be torch.int64\n \n print(x.get().dtype) # torch.int64\n <denchmark-h:h2>Expected Behavior</denchmark-h>\n \n should be torch.int64\n <denchmark-h:h2>Screenshots</denchmark-h>\n \n <denchmark-link:https://user-images.githubusercontent.com/39186433/89849067-a9f89380-dbc2-11ea-84aa-6bf791a46b78.png></denchmark-link>\n \n <denchmark-h:h2>System Information</denchmark-h>\n \n \n OS: MAC\n OS Version: Catalina\n Language Version: Python3.7\n Package Manager Version: Conda 4.8.3\n Browser (if applicable): [e.g. Google Chrome]\n Browser Version (if applicable): [e.g. 81.0.4044.138]\n \n <denchmark-h:h2>Additional Context</denchmark-h>\n \n \t"}, "comments": {"comments_0": {"comment_id": 1, "comment_author": "marload", "commentT": "2020-08-17T19:48:22Z", "comment_text": "\n \t\tHi <denchmark-link:https://github.com/gmuraru>@gmuraru</denchmark-link>\n  can I take this?\n \t\t"}, "comments_1": {"comment_id": 2, "comment_author": "marload", "commentT": "2020-08-17T20:49:44Z", "comment_text": "\n \t\tSure :D\n \t\t"}}}, "commit": {"commit_id": "7fe9f79ebbc2df5ee7990c0f1fd80e8afcda02fc", "commit_author": "Anubhav Raj Singh", "commitT": "2020-08-22 10:52:33+05:18", "changed_files": {"file_0": {"file_change_type": "MODIFY", "file_Nmethod": 0, "file_old_name": "syft\\frameworks\\torch\\tensors\\interpreters\\native.py", "file_new_name": "syft\\frameworks\\torch\\tensors\\interpreters\\native.py", "hunks": {"hunk_0": {"Ismethod": 0, "added_lines": "948", "deleted_lines": "948"}}}, "file_1": {"file_change_type": "MODIFY", "file_Nmethod": 1, "file_old_name": "test\\torch\\tensors\\test_additive_shared.py", "file_new_name": "test\\torch\\tensors\\test_additive_shared.py", "hunks": {"hunk_0": {"Ismethod": 1, "added_lines": "44", "deleted_lines": null, "method_info": {"method_name": "test_share_get", "method_params": "workers,protocol,dtype,n_workers", "method_startline": "32", "method_endline": "47"}}}}}}}