<commit id='c99e0f0e0eb9885fb42c8bebf70b6b3a533b76db' author='Toby Roseman' date='2020-09-21 17:33:24-07:00'>
	<dmm_unit complexity='None' interfacing='None' size='None'></dmm_unit>
	<modification change_type='MODIFY' old_name='src\python\turicreate\test\test_evaluation.py' new_name='src\python\turicreate\test\test_evaluation.py'>
		<file_info nloc='991' complexity='50' token_count='10162'></file_info>
		<method name='test_auc_multi_class_score' parameters='self'>
				<method_info nloc='38' complexity='4' token_count='397' nesting_level='1' start_line='1168' end_line='1216'></method_info>
			<added_lines>1197,1198,1199,1200,1201,1202,1215,1216</added_lines>
			<deleted_lines>1197,1198,1199,1200,1201,1202,1215,1216</deleted_lines>
		</method>
		<modified_lines>
			<added_lines></added_lines>
			<deleted_lines></deleted_lines>
		</modified_lines>
	</modification>
	<modification change_type='MODIFY' old_name='src\toolkits\evaluation\evaluation_interface-inl.hpp' new_name='src\toolkits\evaluation\evaluation_interface-inl.hpp'>
		<file_info nloc='1210' complexity='233' token_count='8637'></file_info>
		<modified_lines>
			<added_lines>1483</added_lines>
			<deleted_lines>1483</deleted_lines>
		</modified_lines>
	</modification>
</commit>
