<bug id='66' author='damianmoore' open_date='2019-01-27T15:14:17Z' closed_time='2019-05-20T19:43:03Z'>
	<summary>Same photo appears multiple times when selecting an object tag that has more than one occurrence</summary>
	<description>
A good example of this is when there is more than one tree in a photo and you select "Tree" from the "Objects" filters
	</description>
	<comments>
		<comment id='1' author='damianmoore' date='2019-03-14T18:51:36Z'>
		Probably would be resolved when &lt;denchmark-link:https://github.com/damianmoore/photonix/issues/70&gt;#70&lt;/denchmark-link&gt;
 is implemented
		</comment>
		<comment id='2' author='damianmoore' date='2019-05-20T19:43:00Z'>
		Fixed in &lt;denchmark-link:https://github.com/damianmoore/photonix/commit/196e55dac455fcf43bd5ee219748e6680cdcff3a&gt;196e55d&lt;/denchmark-link&gt;

		</comment>
	</comments>
</bug>