<commit id='94008233957a49c4a1f708da2122d5059957f6cb' author='Wenwei Zhang' date='2020-08-22 17:51:39+08:00'>
	<dmm_unit complexity='None' interfacing='None' size='None'></dmm_unit>
	<modification change_type='MODIFY' old_name='mmdet\models\roi_heads\mask_heads\fcn_mask_head.py' new_name='mmdet\models\roi_heads\mask_heads\fcn_mask_head.py'>
		<file_info nloc='230' complexity='21' token_count='1795'></file_info>
		<modified_lines>
			<added_lines>183,184,185,186,187,188,189,190,191</added_lines>
			<deleted_lines>183,184</deleted_lines>
		</modified_lines>
	</modification>
</commit>
