{"BR": {"BR_id": "2355", "BR_author": "FadyEssam", "BRopenT": "2020-07-20T17:39:16Z", "BRcloseT": "2020-08-20T15:27:49Z", "BR_text": {"BRsummary": "fairseq-generate not printing score", "BRdescription": "\n \n \n \n fairseq/fairseq/bleu.py\n \n \n          Line 58\n       in\n       93f5128\n \n \n \n \n \n \n  return self.sacrebleu.corpus_bleu(self.sys, [self.ref]) \n \n \n \n \n \n I think .format() should be added to the return line as the latest sacrebleu.corpus_bleu() now returns an object not a string\n \t"}, "comments": {"comments_0": {"comment_id": 1, "comment_author": "FadyEssam", "commentT": "2020-07-26T07:57:20Z", "comment_text": "\n \t\tWe are held up because of this as well. When are you planning on pushing this change?\n \t\t"}}}, "commit": {"commit_id": "627ccc83700782139a02c429fce87b5c11894b18", "commit_author": "Fady Essam", "commitT": "2020-08-04 08:41:27-07:00", "commit_complexity": {"commit_NLOC": "None", "commit_CCN": "None", "commit_Nprams": "None"}, "changed_files": {"file_0": {"file_change_type": "MODIFY", "file_Nmethod": 1, "file_old_name": "fairseq\\bleu.py", "file_new_name": "fairseq\\bleu.py", "file_complexity": {"file_NLOC": "100", "file_CCN": "23", "file_NToken": "829"}, "hunks": {"hunk_0": {"Ismethod": 1, "added_lines": "58", "deleted_lines": "58", "method_info": {"method_name": "result_string", "method_params": "self,order", "method_startline": "55", "method_endline": "58", "method_complexity": {"method_NLOC": "4", "method_CCN": "2", "method_NToken": "37", "method_nesting_level": "1"}}}}}}}}