{"BR": {"BR_id": "17839", "BR_author": "sxjscience", "BRopenT": "2020-03-15T18:51:54Z", "BRcloseT": "2020-04-11T22:01:54Z", "BR_text": {"BRsummary": "[Numpy] Cannot mix int32 and int64", "BRdescription": "\n Code:\n import mxnet as mx\n mx.npx.set_np()\n a = mx.np.ones((10,), dtype=mx.np.int32)\n b = mx.np.ones((10,), dtype=mx.np.int64)\n c = a * b\n print(c)\n Error:\n <denchmark-code>MXNetError: Operator _npi_multiply does not support combination of int with long long yet...\n </denchmark-code>\n \n \t"}, "comments": {"comments_0": {"comment_id": 1, "comment_author": "sxjscience", "commentT": "2020-04-08T23:10:05Z", "comment_text": "\n \t\tFixed by <denchmark-link:https://github.com/apache/incubator-mxnet/pull/17921>#17921</denchmark-link>\n \n \t\t"}}}, "commit": {"commit_id": "d97dead74e43ef33861916ac14b4979ce3c98dde", "commit_author": "JiangZhaoh", "commitT": "2020-04-08 16:07:01-07:00", "commit_complexity": {"commit_NLOC": "0.0", "commit_CCN": "0.0", "commit_Nprams": "0.08108108108108109"}, "changed_files": {"file_0": {"file_change_type": "MODIFY", "file_Nmethod": 0, "file_old_name": "src\\operator\\numpy\\np_elemwise_broadcast_op.cc", "file_new_name": "src\\operator\\numpy\\np_elemwise_broadcast_op.cc", "file_complexity": {"file_NLOC": "110", "file_CCN": "4", "file_NToken": "1023"}, "hunks": {"hunk_0": {"Ismethod": 0, "added_lines": "78,79,80,81", "deleted_lines": null}}}, "file_1": {"file_change_type": "MODIFY", "file_Nmethod": 3, "file_old_name": "src\\operator\\numpy\\np_elemwise_broadcast_op.h", "file_new_name": "src\\operator\\numpy\\np_elemwise_broadcast_op.h", "file_complexity": {"file_NLOC": "483", "file_CCN": "70", "file_NToken": "4866"}, "hunks": {"hunk_0": {"Ismethod": 1, "added_lines": "291,292,293,294,295,296,297,298,299,300,301,302,303,304,305,306,307,308,309,310,311,342,343,344,345,346,347,348,349,350,351,352,353,354,355,356,357,358,359,360,361,362", "deleted_lines": "255", "method_info": {"method_name": "mxnet::op::MixedBinaryBroadcastCompute", "method_params": "attrs,ctx,inputs,req,outputs", "method_startline": "236", "method_endline": "367", "method_complexity": {"method_NLOC": "126", "method_CCN": "19", "method_NToken": "1466", "method_nesting_level": "2"}}}, "hunk_1": {"Ismethod": 1, "added_lines": "427,428,429,430,431,432,433,434,435,436,437,438,439,440,441,442,443,444,445,446,447,448,449,450", "deleted_lines": null, "method_info": {"method_name": "mxnet::op::NumpyBinaryBroadcastComputeWithBool", "method_params": "attrs,ctx,inputs,req,outputs", "method_startline": "407", "method_endline": "457", "method_complexity": {"method_NLOC": "44", "method_CCN": "7", "method_NToken": "479", "method_nesting_level": "2"}}}, "hunk_2": {"Ismethod": 1, "added_lines": null, "deleted_lines": "156", "method_info": {"method_name": "mxnet::op::MixedBinaryElemwiseCompute", "method_params": "attrs,ctx,inputs,req,outputs", "method_startline": "143", "method_endline": "172", "method_complexity": {"method_NLOC": "28", "method_CCN": "7", "method_NToken": "297", "method_nesting_level": "2"}}}}}, "file_2": {"file_change_type": "MODIFY", "file_Nmethod": 2, "file_old_name": "tests\\python\\unittest\\test_numpy_op.py", "file_new_name": "tests\\python\\unittest\\test_numpy_op.py", "file_complexity": {"file_NLOC": "7244", "file_CCN": "1740", "file_NToken": "80465"}, "hunks": {"hunk_0": {"Ismethod": 1, "added_lines": "2427,2428,2483,2484,2485,2486,2487,2488", "deleted_lines": null, "method_info": {"method_name": "test_np_mixed_precision_binary_funcs", "method_params": "", "method_startline": "2393", "method_endline": "2488", "method_complexity": {"method_NLOC": "38", "method_CCN": "9", "method_NToken": "496", "method_nesting_level": "0"}}}, "hunk_1": {"Ismethod": 1, "added_lines": "2427,2428", "deleted_lines": null, "method_info": {"method_name": "test_np_mixed_precision_binary_funcs.check_mixed_precision_binary_func", "method_params": "func,low,high,lshape,rshape,lgrad,rgrad,ltype,rtype", "method_startline": "2396", "method_endline": "2449", "method_complexity": {"method_NLOC": "46", "method_CCN": "14", "method_NToken": "509", "method_nesting_level": "1"}}}}}}}}