<bug id='391' author='walton-wang929' open_date='2020-02-06T14:19:04Z' closed_time='2020-12-15T20:58:04Z'>
	<summary>core dumped error</summary>
	<description>
when i import onnx and tensorrt together, it would create core dumped error. what's wrong with my docker image.
root@e23c27fc5af4:/workspace/img_17_class_porn_new/onnx_tensorrt_new# python3
Python 3.6.9 (default, Nov  7 2019, 10:44:02)
[GCC 8.3.0] on linux
Type "help", "copyright", "credits" or "license" for more information.



import onnx
import tensorrt
Segmentation fault (core dumped)



root@e23c27fc5af4:/workspace/img_17_class_porn_new/onnx_tensorrt_new# python3
Python 3.6.9 (default, Nov  7 2019, 10:44:02)
[GCC 8.3.0] on linux
Type "help", "copyright", "credits" or "license" for more information.



import tensorrt
tensorrt.version
'6.0.1.5'
import onnx
Segmentation fault (core dumped)



root@e23c27fc5af4:/workspace/img_17_class_porn_new/onnx_tensorrt_new# python3
Python 3.6.9 (default, Nov  7 2019, 10:44:02)
[GCC 8.3.0] on linux
Type "help", "copyright", "credits" or "license" for more information.



import onnx
onnx.version
'1.5.0'
import tensorrt
Segmentation fault (core dumped)



	</description>
	<comments>
		<comment id='1' author='walton-wang929' date='2020-02-06T14:19:31Z'>
		need your help !!
		</comment>
		<comment id='2' author='walton-wang929' date='2020-09-22T01:27:50Z'>
		have you solved this problem? I met the same one!
		</comment>
		<comment id='3' author='walton-wang929' date='2020-12-15T20:57:55Z'>
		Can you upgrade to a later TRT version? This issue should no longer occur with later TRT releases.
		</comment>
	</comments>
</bug>