<commit id='d7a695cb33b5a0db837b279b7c4cc3437acdab72' author='Nadav Bar' date='2017-04-03 17:34:21+03:00'>
	<dmm_unit complexity='1.0' interfacing='1.0' size='0.0'></dmm_unit>
	<modification change_type='MODIFY' old_name='src\lib\detection_algorithms\yolo\exporter.js' new_name='src\lib\detection_algorithms\yolo\exporter.js'>
		<file_info nloc='133' complexity='27' token_count='1044'></file_info>
		<method name='exportFrame' parameters='frameFileName,frameBuffer,tags'>
				<method_info nloc='3' complexity='1' token_count='22' nesting_level='0' start_line='116' end_line='164'></method_info>
			<added_lines>128,129,130,137,143,144,145,146,160</added_lines>
			<deleted_lines>132,133,139</deleted_lines>
		</method>
		<method name='(anonymous)' parameters=''>
				<method_info nloc='8' complexity='1' token_count='40' nesting_level='0' start_line='117' end_line='163'></method_info>
			<added_lines>128,129,130,137,143,144,145,146,160</added_lines>
			<deleted_lines>132,133,139</deleted_lines>
		</method>
		<method name='init' parameters=''>
				<method_info nloc='4' complexity='1' token_count='23' nesting_level='0' start_line='52' end_line='103'></method_info>
			<added_lines>53,54</added_lines>
			<deleted_lines></deleted_lines>
		</method>
		<method name='saveBBoxesData' parameters='cb'>
				<method_info nloc='18' complexity='3' token_count='195' nesting_level='0' start_line='124' end_line='141'></method_info>
			<added_lines>128,129,130,137</added_lines>
			<deleted_lines>132,133,139</deleted_lines>
		</method>
		<method name='updateFilesList' parameters='cb'>
				<method_info nloc='13' complexity='3' token_count='86' nesting_level='0' start_line='142' end_line='154'></method_info>
			<added_lines>143,144,145,146</added_lines>
			<deleted_lines></deleted_lines>
		</method>
		<method name='Exporter' parameters='exportDirPath,classes,taggedFramesCount,frameWidth,frameHeight,testSplit'>
				<method_info nloc='23' complexity='3' token_count='188' nesting_level='0' start_line='26' end_line='165'></method_info>
			<added_lines>53,54,128,129,130,137,143,144,145,146,160</added_lines>
			<deleted_lines>132,133,139</deleted_lines>
		</method>
		<modified_lines>
			<added_lines>13</added_lines>
			<deleted_lines>13</deleted_lines>
		</modified_lines>
	</modification>
</commit>
